rp2040link/__init__.py
rp2040link/binary.py
rp2040link/cli.py
rp2040link/diag.py
rp2040link/enums.py
rp2040link/exceptions.py
rp2040link/gpio.py
rp2040link/i2c.py
rp2040link/inputs.py
rp2040link/neopixel.py
rp2040link/pico.py
rp2040link/pwm.py
rp2040link/servo.py
rp2040link/setup_input.py
rp2040link/setup_output.py
rp2040link/spi.py
rp2040link/utils.py
rp2040link/waitbox.py
rp2040link-0.1.4.dist-info/licenses/LICENSE
rp2040link-0.1.4.dist-info/METADATA
rp2040link-0.1.4.dist-info/WHEEL
rp2040link-0.1.4.dist-info/entry_points.txt
rp2040link-0.1.4.dist-info/top_level.txt
rp2040link-0.1.4.dist-info/RECORD
