Metadata-Version: 2.4
Name: rp2040link
Version: 0.1.4
Summary: A high-level, polarity-aware Python controller for Raspberry Pi Pico (RP2040) powered by Telemetrix.
Author-email: Okhtay <okhtaymp@proton.me>
License-Expression: MIT
Project-URL: Homepage, https://github.com/okhtaymp/rp2040link
Project-URL: Repository, https://github.com/okhtaymp/rp2040link
Project-URL: Issues, https://github.com/okhtaymp/rp2040link/issues
Keywords: rp2040,pico,raspberry-pi-pico,telemetrix,gpio,serial,automation
Classifier: Development Status :: 3 - Alpha
Classifier: Intended Audience :: Developers
Classifier: Programming Language :: Python :: 3
Classifier: Programming Language :: Python :: 3 :: Only
Classifier: Topic :: Software Development :: Embedded Systems
Classifier: Topic :: System :: Hardware
Requires-Python: >=3.9
License-File: LICENSE
Requires-Dist: telemetrix-rpi-pico>=1.5.1
Requires-Dist: pyserial>=3.5
Provides-Extra: dev
Requires-Dist: pytest>=8.0; extra == "dev"
Requires-Dist: ruff>=0.4; extra == "dev"
Requires-Dist: mypy>=1.8; extra == "dev"
Requires-Dist: build>=1.2; extra == "dev"
Requires-Dist: twine>=5.0; extra == "dev"
Dynamic: license-file
